poetry_plugin_import/__init__.py
poetry_plugin_import/plugins.py
poetry_plugin_import/utils.py
poetry_plugin_import-0.1.2.dist-info/LICENSE
poetry_plugin_import-0.1.2.dist-info/METADATA
poetry_plugin_import-0.1.2.dist-info/WHEEL
poetry_plugin_import-0.1.2.dist-info/entry_points.txt
poetry_plugin_import-0.1.2.dist-info/RECORD
