Metadata-Version: 2.1
Name: poetry-plugin-import
Version: 0.1.2
Summary: A Poetry plugin that import dependencies from requirements.txt
Author: Neriberto C.Prado
Author-email: neriberto@gmail.com
Requires-Python: >=3.7,<4.0
Classifier: Programming Language :: Python :: 3
Classifier: Programming Language :: Python :: 3.7
Classifier: Programming Language :: Python :: 3.8
Classifier: Programming Language :: Python :: 3.9
Classifier: Programming Language :: Python :: 3.10
Classifier: Programming Language :: Python :: 3.11
Requires-Dist: poetry (>=1.5.1,<2.0.0)
Requires-Dist: poetry-core (>=1.6.1,<2.0.0)
